rtc/__init__.py
rtc/py.typed
rtc/app/__init__.py
rtc/app/decorator.py
rtc/app/exc.py
rtc/app/hash.py
rtc/app/metadata.py
rtc/app/serializer.py
rtc/app/service.py
rtc/app/storage.py
rtc/app/types.py
rtc/infra/__init__.py
rtc/infra/adapters/__init__.py
rtc/infra/adapters/metadata/__init__.py
rtc/infra/adapters/metadata/bad.py
rtc/infra/adapters/metadata/blackhole.py
rtc/infra/adapters/metadata/dict.py
rtc/infra/adapters/metadata/redis.py
rtc/infra/adapters/storage/__init__.py
rtc/infra/adapters/storage/bad.py
rtc/infra/adapters/storage/blackhole.py
rtc/infra/adapters/storage/dict.py
rtc/infra/adapters/storage/redis.py
rtc/infra/controllers/__init__.py
rtc/infra/controllers/lib.py
redis_tagged_cache-0.12.1.dist-info/METADATA
redis_tagged_cache-0.12.1.dist-info/WHEEL
redis_tagged_cache-0.12.1.dist-info/licenses/LICENSE
redis_tagged_cache-0.12.1.dist-info/RECORD
