Metadata-Version: 2.4
Name: redis-tagged-cache
Version: 0.12.1
Author-email: Fabien MARTY <fabien.marty@botify.com>
License-File: LICENSE
Requires-Python: ~=3.7
Requires-Dist: redis>=3.2.0
Requires-Dist: wrapt>=1.16.0
